bpsymbol/__init__.py
bpsymbol/abstract.py
bpsymbol/bloomberg.py
bpsymbol/symbol.py
bpsymbol/utils.py
bpsymbol-0.0.2.dist-info/METADATA
bpsymbol-0.0.2.dist-info/WHEEL
bpsymbol-0.0.2.dist-info/top_level.txt
bpsymbol-0.0.2.dist-info/RECORD
