Metadata-Version: 2.1
Name: bpsymbol
Version: 0.0.2
Summary: Symbol Manager for Multiple data sources
Home-page: https://github.com/blackpaper9973/bpsymbol
Author: Kim jinho
Author-email: blackpaper9973@gmail.com
License: UNKNOWN
Download-URL: https://githur.com/blackpaper9973/bpsymbol/archive/master.gz
Keywords: financial data,quant
Platform: UNKNOWN
Requires-Python: >=3
